mtly/__init__.py
mtly/motley.py
mtly/motley_settings/__init__.py
mtly/motley_settings/color_combos.py
mtly/motley_settings/enums/__init__.py
mtly/motley_settings/enums/enum_color_combos.py
mtly/motley_settings/enums/enum_colors.py
mtly/motley_settings/enums/enum_styles.py
mtly-14.1.1.dist-info/LICENSE
mtly-14.1.1.dist-info/METADATA
mtly-14.1.1.dist-info/WHEEL
mtly-14.1.1.dist-info/RECORD
